easy_deployer/__init__.py
easy_deployer/cli.py
easy_deployer/utils_old.py
easy_deployer/hosting/__init__.py
easy_deployer/hostings/__init__.py
easy_deployer/hostings/heroku.py
easy_deployer/utilities/__init__.py
easy_deployer/utilities/interface.py
easy_deployer/utilities/process.py
easy_deployer/utilities/terminal.py
easy_deployer/version_control/__init__.py
easy_deployer/version_control/github-old.py
easy_deployer/version_control/github.py
easy_deployer-1.0.7.dist-info/LICENSE.txt
easy_deployer-1.0.7.dist-info/METADATA
easy_deployer-1.0.7.dist-info/WHEEL
easy_deployer-1.0.7.dist-info/entry_points.txt
easy_deployer-1.0.7.dist-info/top_level.txt
easy_deployer-1.0.7.dist-info/RECORD
