Metadata-Version: 2.1
Name: easy-deployer
Version: 1.0.7
Summary: A package to simplify and quickly deploy your project/app/folders to the supported platforms.
Home-page: https://github.com/medamine980/easy-deployer
Author: Mohamed-Amine Benali
Author-email: benali.medamine2002@gmail.com
License: MIT
Keywords: python,github,github-deployer,heroku,heroku-deployer,deploy,easy,easy-deployer,simple,simple-deployer
Classifier: License :: OSI Approved :: MIT License
Classifier: Programming Language :: Python
Classifier: Programming Language :: Python :: 3.7
Classifier: Programming Language :: Python :: 3.11
License-File: LICENSE.txt
Requires-Dist: keyboard
Requires-Dist: pipreqs
Requires-Dist: Click
Requires-Dist: InquirerPy
